radio_mlbee_client/__init__.py
radio_mlbee_client/__main__.py
radio_mlbee_client/radio_mlbee_client.py
radio_mlbee_client/radio_mlbee_client.py--
radio_mlbee_client-0.1.0a0.dist-info/entry_points.txt
radio_mlbee_client-0.1.0a0.dist-info/LICENSE
radio_mlbee_client-0.1.0a0.dist-info/WHEEL
radio_mlbee_client-0.1.0a0.dist-info/METADATA
radio_mlbee_client-0.1.0a0.dist-info/RECORD
