Metadata-Version: 2.1
Name: radio-mlbee-client
Version: 0.1.0a0
Summary: radio_mlbee_client
Home-page: https://github.com/ffreemt/radio-mlbee-client
License: MIT
Author: ffreemt
Requires-Python: >=3.8.3,<4.0.0
Classifier: License :: OSI Approved :: MIT License
Classifier: Programming Language :: Python :: 3
Classifier: Programming Language :: Python :: 3.10
Classifier: Programming Language :: Python :: 3.9
Requires-Dist: httpx (>=0.23.0,<0.24.0)
Requires-Dist: icecream (>=2.1.1,<3.0.0)
Requires-Dist: install (>=1.3.5,<2.0.0)
Requires-Dist: logzero (>=1.7.0,<2.0.0)
Requires-Dist: set-loglevel (>=0.1.2,<0.2.0)
Requires-Dist: tenacity (>=8.0.1,<9.0.0)
Requires-Dist: typer (>=0.4.1,<0.5.0)
Project-URL: Repository, https://github.com/ffreemt/radio-mlbee-client
